contextual_retrieval/__init__.py
contextual_retrieval/bm25.py
contextual_retrieval/context_generator.py
contextual_retrieval/embedding_models.py
contextual_retrieval/reranker.py
contextual_retrieval/retrieval.py
contextual_retrieval/utils.py
contextual_retrieval/vector_store.py
contextual_retrieval-0.1.1.dist-info/LICENCE
contextual_retrieval-0.1.1.dist-info/METADATA
contextual_retrieval-0.1.1.dist-info/WHEEL
contextual_retrieval-0.1.1.dist-info/top_level.txt
contextual_retrieval-0.1.1.dist-info/RECORD
