Metadata-Version: 2.1
Name: contextual_retrieval
Version: 0.1.1
Summary: An open-source Python RAG library for Contextual Retrieval
Home-page: https://github.com/HamadaFMahdi/contextual-retrieval
Author: Hamada Fadil Mahdi
Author-email: hamadamahdi2014@gmail.com
Classifier: Development Status :: 3 - Alpha
Classifier: Intended Audience :: Developers
Classifier: License :: OSI Approved :: MIT License
Classifier: Operating System :: OS Independent
Classifier: Programming Language :: Python :: 3
Classifier: Programming Language :: Python :: 3.7
Classifier: Programming Language :: Python :: 3.8
Classifier: Programming Language :: Python :: 3.9
Classifier: Topic :: Scientific/Engineering :: Artificial Intelligence
Requires-Python: >=3.7
License-File: LICENCE
Requires-Dist: aiohttp >=3.7.4
Requires-Dist: faiss-cpu >=1.7.2
Requires-Dist: nltk >=3.6.2
Requires-Dist: numpy >=1.21.0
Requires-Dist: openai >=0.27.0
Requires-Dist: rank-bm25 >=0.2.2
Requires-Dist: requests >=2.25.1
Requires-Dist: sentence-transformers >=2.2.0
Requires-Dist: torch >=1.9.0
Requires-Dist: tqdm >=4.62.0
Requires-Dist: transformers >=4.10.0
